main/__init__.py
main/get_quote.py
main/quotes.py
stoic_quotes-0.1.0.dist-info/WHEEL
stoic_quotes-0.1.0.dist-info/METADATA
stoic_quotes-0.1.0.dist-info/RECORD
